greps/__init__.py
greps/greps.py
greps-1.0.4.dist-info/LICENSE
greps-1.0.4.dist-info/METADATA
greps-1.0.4.dist-info/WHEEL
greps-1.0.4.dist-info/RECORD
